esub.py
esub-0.0.6.dist-info/DESCRIPTION.rst
esub-0.0.6.dist-info/METADATA
esub-0.0.6.dist-info/RECORD
esub-0.0.6.dist-info/WHEEL
esub-0.0.6.dist-info/entry_points.txt
esub-0.0.6.dist-info/metadata.json
esub-0.0.6.dist-info/top_level.txt
