Metadata-Version: 2.0
Name: esub
Version: 0.0.6
Summary: esub python client library
Home-page: https://github.com/ccpgames/esub-client/
Author: Adam Talsma
Author-email: se-adam@talsma@ccpgames.com
License: UNKNOWN
Download-URL: https://github.com/ccpgames/esub-client/
Platform: UNKNOWN
Classifier: Development Status :: 2 - Pre-Alpha
Classifier: Operating System :: POSIX :: Linux
Classifier: License :: OSI Approved :: MIT License
Classifier: Programming Language :: Python :: 3
Requires-Dist: requests
Requires-Dist: websockets
Requires-Dist: docopt
